flow_ai_sdk/__init__.py
flow_ai_sdk/_base_client.py
flow_ai_sdk/_client.py
flow_ai_sdk/_compat.py
flow_ai_sdk/_constants.py
flow_ai_sdk/_exceptions.py
flow_ai_sdk/_files.py
flow_ai_sdk/_models.py
flow_ai_sdk/_qs.py
flow_ai_sdk/_resource.py
flow_ai_sdk/_response.py
flow_ai_sdk/_streaming.py
flow_ai_sdk/_types.py
flow_ai_sdk/_version.py
flow_ai_sdk/py.typed
flow_ai_sdk/_utils/__init__.py
flow_ai_sdk/_utils/_logs.py
flow_ai_sdk/_utils/_proxy.py
flow_ai_sdk/_utils/_reflection.py
flow_ai_sdk/_utils/_resources_proxy.py
flow_ai_sdk/_utils/_streams.py
flow_ai_sdk/_utils/_sync.py
flow_ai_sdk/_utils/_transform.py
flow_ai_sdk/_utils/_typing.py
flow_ai_sdk/_utils/_utils.py
flow_ai_sdk/lib/.keep
flow_ai_sdk/resources/__init__.py
flow_ai_sdk/resources/api_info.py
flow_ai_sdk/resources/api_keys.py
flow_ai_sdk/resources/batches.py
flow_ai_sdk/resources/clerk_webhooks.py
flow_ai_sdk/resources/datasets.py
flow_ai_sdk/resources/health.py
flow_ai_sdk/resources/jobs.py
flow_ai_sdk/resources/stages.py
flow_ai_sdk/resources/test_cases.py
flow_ai_sdk/resources/validation_tasks.py
flow_ai_sdk/resources/validations.py
flow_ai_sdk/resources/auth/__init__.py
flow_ai_sdk/resources/auth/auth.py
flow_ai_sdk/resources/auth/sdk.py
flow_ai_sdk/resources/auth/validators.py
flow_ai_sdk/resources/integrations/__init__.py
flow_ai_sdk/resources/integrations/integrations.py
flow_ai_sdk/resources/integrations/prefect.py
flow_ai_sdk/resources/projects/__init__.py
flow_ai_sdk/resources/projects/jobs.py
flow_ai_sdk/resources/projects/projects.py
flow_ai_sdk/resources/projects/validators.py
flow_ai_sdk/resources/users/__init__.py
flow_ai_sdk/resources/users/me.py
flow_ai_sdk/resources/users/users.py
flow_ai_sdk/resources/validator_tasks/__init__.py
flow_ai_sdk/resources/validator_tasks/validations.py
flow_ai_sdk/resources/validator_tasks/validator_tasks.py
flow_ai_sdk/types/__init__.py
flow_ai_sdk/types/api_info_retrieve_response.py
flow_ai_sdk/types/api_key_create_params.py
flow_ai_sdk-4.0.0.dist-info/METADATA
flow_ai_sdk-4.0.0.dist-info/WHEEL
flow_ai_sdk-4.0.0.dist-info/licenses/LICENSE
flow_ai_sdk-4.0.0.dist-info/RECORD
